anthemav_hyralex/__init__.py
anthemav_hyralex/connection.py
anthemav_hyralex/protocol.py
anthemav_hyralex/tools.py
anthemav_hyralex-1.0.0.dist-info/LICENSE
anthemav_hyralex-1.0.0.dist-info/METADATA
anthemav_hyralex-1.0.0.dist-info/WHEEL
anthemav_hyralex-1.0.0.dist-info/entry_points.txt
anthemav_hyralex-1.0.0.dist-info/top_level.txt
anthemav_hyralex-1.0.0.dist-info/zip-safe
anthemav_hyralex-1.0.0.dist-info/RECORD
