Metadata-Version: 2.1
Name: anthemav-hyralex
Version: 1.0.0
Summary: Forked of anthemav. Python API for controlling Anthem Receivers
Home-page: https://github.com/hyralex/python-anthemav
Author: Hyralex
Author-email: hyralex@gmail.com
License: LICENSE
Platform: UNKNOWN
Classifier: Development Status :: 5 - Production/Stable
Classifier: Intended Audience :: Developers
Classifier: License :: OSI Approved :: MIT License
Classifier: Operating System :: OS Independent
Classifier: Programming Language :: Python
Classifier: Topic :: Software Development :: Libraries :: Python Modules
License-File: LICENSE
